jupyter_contents/__init__.py
jupyter_contents/__main__.py
jupyter_contents/__version__.py
jupyter_contents/application.py
jupyter_contents/application_base.py
jupyter_contents/serverapplication.py
jupyter_contents/content/__init__.py
jupyter_contents/content/contentapp.py
jupyter_contents/content/handlers.py
jupyter_contents/content/gcp/__init__.py
jupyter_contents/content/gcp/content.py
jupyter_contents/content/gcp/test_content.py
jupyter_contents/content/gcp/test_simple.py
jupyter_contents/handlers/__init__.py
jupyter_contents/handlers/base.py
jupyter_contents/handlers/config/__init__.py
jupyter_contents/handlers/config/handler.py
jupyter_contents/handlers/content/__init__.py
jupyter_contents/handlers/content/handler.py
jupyter_contents/handlers/echo/__init__.py
jupyter_contents/handlers/echo/handler.py
jupyter_contents/handlers/index/__init__.py
jupyter_contents/handlers/index/handler.py
jupyter_contents/handlers/ping/__init__.py
jupyter_contents/handlers/ping/handler.py
jupyter_contents/handlers/proxy/__init__.py
jupyter_contents/handlers/proxy/handler.py
jupyter_contents/handlers/relay/__init__.py
jupyter_contents/handlers/relay/handler.py
jupyter_contents/jump/__init__.py
jupyter_contents/jump/jumpapp.py
jupyter_contents/static/README.md
jupyter_contents/templates/index.html
jupyter_contents/tests/__init__.py
jupyter_contents/tests/test_handlers.py
jupyter_contents-0.0.8.data/data/etc/jupyter/jupyter_notebook_config.d/jupyter_contents.json
jupyter_contents-0.0.8.data/data/etc/jupyter/jupyter_server_config.d/jupyter_contents.json
jupyter_contents-0.0.8.dist-info/METADATA
jupyter_contents-0.0.8.dist-info/WHEEL
jupyter_contents-0.0.8.dist-info/entry_points.txt
jupyter_contents-0.0.8.dist-info/licenses/LICENSE
jupyter_contents-0.0.8.dist-info/RECORD
